omsens-1.0.2.data/purelib/OMSens/__init__.py
omsens-1.0.2.data/purelib/OMSens/build_hooks.py
omsens-1.0.2.data/purelib/OMSens/individual_sens_calculator.py
omsens-1.0.2.data/purelib/OMSens/interactive_plot.py
omsens-1.0.2.data/purelib/OMSens/multiparam_sweep.py
omsens-1.0.2.data/purelib/OMSens/plot_predefined_heatmaps.py
omsens-1.0.2.data/purelib/OMSens/predefined_plots_wp2.py
omsens-1.0.2.data/purelib/OMSens/predefined_plots_wp3.py
omsens-1.0.2.data/purelib/OMSens/vectorial_analysis.py
omsens-1.0.2.data/purelib/OMSens/world3_scenarios_sweeps_multiparam.py
omsens-1.0.2.data/purelib/OMSens/world3_scenarios_sweeps_uniparam.py
omsens-1.0.2.data/purelib/OMSens/analysis/__init__.py
omsens-1.0.2.data/purelib/OMSens/analysis/indiv_sens.py
omsens-1.0.2.data/purelib/OMSens/filesystem/__init__.py
omsens-1.0.2.data/purelib/OMSens/filesystem/files_aux.py
omsens-1.0.2.data/purelib/OMSens/fortran_interface/Curvif.for
omsens-1.0.2.data/purelib/OMSens/fortran_interface/Curvif_simplified.f90
omsens-1.0.2.data/purelib/OMSens/fortran_interface/Rut.for
omsens-1.0.2.data/purelib/OMSens/fortran_interface/Rutf.for
omsens-1.0.2.data/purelib/OMSens/fortran_interface/curvif_simplified.cpython-313-x86_64-linux-gnu.so
omsens-1.0.2.data/purelib/OMSens/fortran_interface/curvif_simplified.pyf
omsens-1.0.2.data/purelib/OMSens/fortran_interface/readme.txt
omsens-1.0.2.data/purelib/OMSens/misc/csv_output_to_csv_matrix_converter.py
omsens-1.0.2.data/purelib/OMSens/misc/parametersFromXMLToCSV.py
omsens-1.0.2.data/purelib/OMSens/modelica_interface/__init__.py
omsens-1.0.2.data/purelib/OMSens/modelica_interface/build_model.py
omsens-1.0.2.data/purelib/OMSens/modelica_interface/compiled_model.py
omsens-1.0.2.data/purelib/OMSens/modelica_interface/run_omc.py
omsens-1.0.2.data/purelib/OMSens/mos_writer/__init__.py
omsens-1.0.2.data/purelib/OMSens/mos_writer/calculate_sensitivities_mos_writer.py
omsens-1.0.2.data/purelib/OMSens/mos_writer/formulas.py
omsens-1.0.2.dist-info/METADATA
omsens-1.0.2.dist-info/WHEEL
omsens-1.0.2.dist-info/top_level.txt
omsens-1.0.2.dist-info/RECORD
