Metadata-Version: 2.4
Name: OMSens
Version: 1.0.2
Summary: OpenModelica sensitivity analysis and optimization module
Author-email: Rodrigo Castro <rcastro@dc.uba.ar>
Maintainer-email: Adeel Asghar <adeel.asghar@liu.se>
License: --- Start of Definition of OSMC Public License ---
Project-URL: Homepage, http://openmodelica.org/
Project-URL: Documentation, https://openmodelica.org/doc/OpenModelicaUsersGuide/latest/parametersensitivity.html#single-and-multi-parameter-sensitivities-with-omsens
Project-URL: Source Code, https://github.com/OpenModelica/OMSens
Project-URL: Issues, https://github.com/OpenModelica/OMSens/issues
Project-URL: Release Notes, https://github.com/OpenModelica/OMSens/releases
Project-URL: Download, https://pypi.org/project/OMSens/#files
Requires-Python: >=3.12
Requires-Dist: six
Requires-Dist: pytest
Requires-Dist: matplotlib
Requires-Dist: kiwisolver
Requires-Dist: Pillow
Requires-Dist: numpy
Requires-Dist: pandas
